[
{
    "autor" : "chubameubilau",
    "comentario" : "Uma vez minha mãe saiu para caçar água viva",
    "data" : "· 2 days ago",
    "respostas" : [{
        "autor_resp": "AutordaResposta1",
        "comentario_resp": "Mas você tem que aprender a língua dos peixes para falar com eles, então você vai ter que tirar essa informação no cu",
        "data_resp" : "· 0 day ago"
    },
    {
        "autor_resp": "AutordaResposta2",
        "comentario_resp": "Resposta2",
        "data_resp" : "· 1 day ago"
    }]
},
{
    "autor" : "saco_pega_no_meusaco",
    "comentario" : "Senta menina, encaixa na pica vaiiii, rebola menina, senta maria vaiii. Você pode bemm deixar querendo maisss. sen sen sen senta maria vaiii.",
    "data" : "· 6 days ago",
    "respostas" : [{
        "autor_resp": "",
        "comentario_resp": "",
        "data_resp" : ""
    },
    {
        "autor_resp": "",
        "comentario_resp": "",
        "data_resp" : ""
    }]
},
{
    "autor" : "moleque_sapeca",
    "comentario" : "Moleeque transante, e ta começando a noitada, hooje a noite só vai rolar vara, gabriela cor de canela, essa menina aoksdapdkp ela.",
    "data" : "· 3 days ago",
    "respostas" : [{
        "autor_resp": "AutordaResposta5",
        "comentario_resp": "Resposta5",
        "data_resp" : "· 4 day ago"
    },
    {
        "autor_resp": "",
        "comentario_resp": "",
        "data_resp" : ""
    }]
}
]